BacenAPI/__init__.py
BacenAPI/bacen_search.py
BacenAPI/bacen_series.py
BacenAPI/bacen_url.py
BacenAPI/Date/dataset.txt
bacenapi-0.3.0.dist-info/licenses/License.md
bacenapi-0.3.0.dist-info/METADATA
bacenapi-0.3.0.dist-info/WHEEL
bacenapi-0.3.0.dist-info/top_level.txt
bacenapi-0.3.0.dist-info/RECORD
