Metadata-Version: 2.4
Name: BacenAPI
Version: 0.3.0
Summary: Package to access time series data from the Central Bank of Brazil via API
Home-page: https://github.com/LissandroSousa/BacenAPI.py
Author: Paulo Icaro, Lissandro Sousa, Francisco Gildermir
Author-email: lisandrosousa54@gmail.com
Classifier: Programming Language :: Python :: 3
Classifier: License :: OSI Approved :: MIT License
Classifier: Operating System :: OS Independent
Requires-Python: >=3.7
License-File: License.md
Requires-Dist: pandas
Requires-Dist: requests
Dynamic: author
Dynamic: author-email
Dynamic: classifier
Dynamic: description
Dynamic: description-content-type
Dynamic: home-page
Dynamic: license-file
Dynamic: requires-dist
Dynamic: requires-python
Dynamic: summary
